{
    "input": {
        "params": {
            "pattern": "@black_format"
        },
        "type": "git_grep"
    },
    "filters": [
        {
            "inverted": false,
            "params": {
                "pattern": ".*\\.py$"
            },
            "type": "regex"
        }
    ],
    "batcher": {
        "params": {
            "metadata": {
                "title": "Black Format",
                "body": "Apply Black formatting to all python files with @black_format"
            }
        },
        "type": "single"
    },
    "transformer": {
        "params": {
            "script": "black",
            "args": [
                "-l",
                "100",
                "<<INPUT>>"
            ],
            "timeout": 360,
            "per_file": 1
        },
        "type": "script"
    },
    "validators": [],
    "commands": [],
    "config": {
        "allowed_validation_level": 0
    },
    "repo": {
        "params": {
            "base_branch_name": "master",
            "full_github_name": "nathro/AutoTransform"
        },
        "type": "github"
    }
}